odoo/addons/pos_lot_selection/README.rst
odoo/addons/pos_lot_selection/__init__.py
odoo/addons/pos_lot_selection/__manifest__.py
odoo/addons/pos_lot_selection/i18n/de.po
odoo/addons/pos_lot_selection/i18n/es.po
odoo/addons/pos_lot_selection/i18n/fr.po
odoo/addons/pos_lot_selection/i18n/it.po
odoo/addons/pos_lot_selection/i18n/pos_lot_selection.pot
odoo/addons/pos_lot_selection/models/__init__.py
odoo/addons/pos_lot_selection/models/pos_session.py
odoo/addons/pos_lot_selection/models/product_product.py
odoo/addons/pos_lot_selection/models/stock_lot.py
odoo/addons/pos_lot_selection/readme/CONTRIBUTORS.md
odoo/addons/pos_lot_selection/readme/DESCRIPTION.md
odoo/addons/pos_lot_selection/readme/USAGE.md
odoo/addons/pos_lot_selection/static/description/icon.png
odoo/addons/pos_lot_selection/static/description/index.html
odoo/addons/pos_lot_selection/static/src/js/EditListPopup.esm.js
odoo/addons/pos_lot_selection/static/src/js/models.esm.js
odoo/addons/pos_lot_selection/static/src/xml/LotSelectorPopup.xml
odoo/addons/pos_lot_selection/static/tests/tours/LotSelection.tour.esm.js
odoo/addons/pos_lot_selection/tests/__init__.py
odoo/addons/pos_lot_selection/tests/test_frontend.py
odoo_addon_pos_lot_selection-17.0.1.0.1.3.dist-info/METADATA
odoo_addon_pos_lot_selection-17.0.1.0.1.3.dist-info/WHEEL
odoo_addon_pos_lot_selection-17.0.1.0.1.3.dist-info/top_level.txt
odoo_addon_pos_lot_selection-17.0.1.0.1.3.dist-info/RECORD
